coinspot/__init__.py
coinspot/coinspot.py
coinspot_py-0.0.1.dist-info/DESCRIPTION.rst
coinspot_py-0.0.1.dist-info/METADATA
coinspot_py-0.0.1.dist-info/RECORD
coinspot_py-0.0.1.dist-info/WHEEL
coinspot_py-0.0.1.dist-info/metadata.json
coinspot_py-0.0.1.dist-info/top_level.txt
