Metadata-Version: 2.0
Name: coinspot-py
Version: 0.0.1
Summary: A python wrapper for the CoinSpot API
Home-page: https://github.com/slavkobojanic/Python-CoinSpot-V2
Author: Slavko Bojanic
Author-email: slavkobojj@gmail.com
License: UNKNOWN
Download-URL: https://github.com/slavkobojanic/Python-CoinSpot-V2/archive/0.0.1.tar.gz
Keywords: python,coinspot,cryptocurrency,bitcoin,api,python3,altcoin
Platform: UNKNOWN
Requires-Python: >=3
Requires-Dist: requests
